MusicUtils-0.1.dev6.dist-info/METADATA
MusicUtils-0.1.dev6.dist-info/RECORD
MusicUtils-0.1.dev6.dist-info/WHEEL
MusicUtils-0.1.dev6.dist-info/entry_points.txt
MusicUtils-0.1.dev6.dist-info/top_level.txt
musicutils/__init__.py
musicutils/utils.py
