Metadata-Version: 2.1
Name: MusicUtils
Version: 0.1.dev6
Summary: Helpful library and command-line-tool         to download music, update metadata, rearrange         files, and other common utilities.
Home-page: https://github.com/hundredrab/musicutils
Author: Sourab Jha
Author-email: jha.sourab@gmail.com
License: MIT
Platform: UNKNOWN
Classifier: Programming Language :: Python :: 3.5
Classifier: License :: OSI Approved :: MIT License
Requires-Python: >=3.4
Requires-Dist: mutagen
Requires-Dist: eyed3
Requires-Dist: youtube-dl
Requires-Dist: lxml
Requires-Dist: bs4
Requires-Dist: requests
